Metadata-Version: 2.1
Name: netservice
Version: 0.3
Summary: Python NetService Library
Home-page: https://netservice.shop
Author: NetService Co
Author-email: sup@netservice.shop
License: MIT
Download-URL: https://github.com/mostafa-vn/netservice.git
Keywords: netservice netservice.shop library python v3
Platform: any
Classifier: Programming Language :: Python :: 3
Classifier: License :: OSI Approved :: MIT License
Classifier: Operating System :: OS Independent
Classifier: Development Status :: 4 - Beta
Classifier: Intended Audience :: Developers
Classifier: Environment :: Console
Classifier: Topic :: Software Development :: Libraries :: Python Modules
